funcs_for_pfs/__init__.py
funcs_for_pfs-0.1.2.dist-info/LICENSE.txt
funcs_for_pfs-0.1.2.dist-info/METADATA
funcs_for_pfs-0.1.2.dist-info/WHEEL
funcs_for_pfs-0.1.2.dist-info/top_level.txt
funcs_for_pfs-0.1.2.dist-info/RECORD
